{
  "entrypoints": [
    "main"
  ],
  "origins": {
    "4608": [
      4608
    ],
    "7459": [
      532,
      3085,
      3089,
      6103,
      7918,
      8610,
      7459
    ],
    "15548885": [
      4138
    ],
    "17896441": [
      532,
      7459,
      7918
    ],
    "59362658": [
      2267
    ],
    "96548635": [
      8392
    ],
    "main": [
      532,
      1303,
      179
    ],
    "runtime~main": [
      179,
      532,
      1303
    ],
    "00b11949": [
      7076
    ],
    "01a85c17": [
      532,
      4013
    ],
    "074c9588": [
      8356
    ],
    "112b66d9": [
      2382
    ],
    "1be78505": [
      532,
      4608
    ],
    "1f391b9e": [
      532,
      7459,
      3085
    ],
    "20623d08": [
      9643
    ],
    "20be1dc7": [
      4717
    ],
    "2bd53048": [
      2472
    ],
    "371a13d2": [
      1066
    ],
    "393be207": [
      7414
    ],
    "4230b848": [
      9000
    ],
    "4dfcf414": [
      3871
    ],
    "52f629a9": [
      1173
    ],
    "6875c492": [
      532,
      7459,
      8610
    ],
    "73664a40": [
      3514
    ],
    "7661071f": [
      9642
    ],
    "77869f04": [
      5440
    ],
    "78027c79": [
      4466
    ],
    "7caa0764": [
      2611
    ],
    "814f3328": [
      2535
    ],
    "84d31fca": [
      4521
    ],
    "8712ed38": [
      8592
    ],
    "8717b14a": [
      948
    ],
    "925b3f96": [
      9003
    ],
    "935f2afb": [
      53
    ],
    "9e4087bc": [
      3608
    ],
    "a6aa9e1f": [
      532,
      7459,
      3089
    ],
    "b26cdafd": [
      3060
    ],
    "b4fe1602": [
      8444
    ],
    "c37ce9b2": [
      8329
    ],
    "c3804f3b": [
      3266
    ],
    "c4f5d8e4": [
      532,
      4195
    ],
    "c91a8ac4": [
      6839
    ],
    "ccc49370": [
      532,
      7459,
      6103
    ],
    "cff4a090": [
      7070
    ],
    "d41956b8": [
      7904
    ],
    "d9f32620": [
      1914
    ],
    "dda638a8": [
      2711
    ],
    "e182be54": [
      3769
    ],
    "e273c56f": [
      2362
    ],
    "e379776a": [
      9174
    ],
    "efa918bb": [
      4441
    ],
    "f20c3c27": [
      2391
    ],
    "f4f34a3a": [
      8636
    ],
    "f5363f6c": [
      6499
    ],
    "ff018aef": [
      1612
    ],
    "styles": [
      179,
      1303,
      3085,
      3089,
      4013,
      4195,
      6103,
      7459,
      7918,
      8610,
      9514,
      532
    ]
  },
  "assets": {
    "53": {
      "js": [
        {
          "file": "assets/js/935f2afb.d8fd12d2.js",
          "hash": "d8e361ac995e8cf4",
          "publicPath": "/cn/assets/js/935f2afb.d8fd12d2.js"
        }
      ]
    },
    "179": {
      "js": [
        {
          "file": "assets/js/main.550bae81.js",
          "hash": "a44bc629da1450b1",
          "publicPath": "/cn/assets/js/main.550bae81.js"
        }
      ]
    },
    "532": {
      "css": [
        {
          "file": "assets/css/styles.5627add0.css",
          "hash": "489eeaf45cba487b",
          "publicPath": "/cn/assets/css/styles.5627add0.css"
        }
      ]
    },
    "948": {
      "js": [
        {
          "file": "assets/js/8717b14a.d34e70e6.js",
          "hash": "3d84c3211c46edcb",
          "publicPath": "/cn/assets/js/8717b14a.d34e70e6.js"
        }
      ]
    },
    "1066": {
      "js": [
        {
          "file": "assets/js/371a13d2.c4972015.js",
          "hash": "ece65037526247f5",
          "publicPath": "/cn/assets/js/371a13d2.c4972015.js"
        }
      ]
    },
    "1173": {
      "js": [
        {
          "file": "assets/js/52f629a9.26d865ed.js",
          "hash": "dda051b0361673ca",
          "publicPath": "/cn/assets/js/52f629a9.26d865ed.js"
        }
      ]
    },
    "1303": {
      "js": [
        {
          "file": "assets/js/runtime~main.e4400e1d.js",
          "hash": "8827fc47416c17c1",
          "publicPath": "/cn/assets/js/runtime~main.e4400e1d.js"
        }
      ]
    },
    "1612": {
      "js": [
        {
          "file": "assets/js/ff018aef.a56a72ff.js",
          "hash": "63fa6d39879052db",
          "publicPath": "/cn/assets/js/ff018aef.a56a72ff.js"
        }
      ]
    },
    "1914": {
      "js": [
        {
          "file": "assets/js/d9f32620.c5cc77ac.js",
          "hash": "c977c11c832146b0",
          "publicPath": "/cn/assets/js/d9f32620.c5cc77ac.js"
        }
      ]
    },
    "2267": {
      "js": [
        {
          "file": "assets/js/59362658.334a3d07.js",
          "hash": "512a395f3138824e",
          "publicPath": "/cn/assets/js/59362658.334a3d07.js"
        }
      ]
    },
    "2362": {
      "js": [
        {
          "file": "assets/js/e273c56f.74205df7.js",
          "hash": "9197bb521ab0f7fa",
          "publicPath": "/cn/assets/js/e273c56f.74205df7.js"
        }
      ]
    },
    "2382": {
      "js": [
        {
          "file": "assets/js/112b66d9.9a88afed.js",
          "hash": "80d9ce4f212e2a27",
          "publicPath": "/cn/assets/js/112b66d9.9a88afed.js"
        }
      ]
    },
    "2391": {
      "js": [
        {
          "file": "assets/js/f20c3c27.8133c9df.js",
          "hash": "da0dee478a82d144",
          "publicPath": "/cn/assets/js/f20c3c27.8133c9df.js"
        }
      ]
    },
    "2472": {
      "js": [
        {
          "file": "assets/js/2bd53048.6c871763.js",
          "hash": "133b49b91e3e6662",
          "publicPath": "/cn/assets/js/2bd53048.6c871763.js"
        }
      ]
    },
    "2535": {
      "js": [
        {
          "file": "assets/js/814f3328.4b673130.js",
          "hash": "fa03a71b8f43ce22",
          "publicPath": "/cn/assets/js/814f3328.4b673130.js"
        }
      ]
    },
    "2611": {
      "js": [
        {
          "file": "assets/js/7caa0764.f3885fb1.js",
          "hash": "b24d3e7e215496d3",
          "publicPath": "/cn/assets/js/7caa0764.f3885fb1.js"
        }
      ]
    },
    "2711": {
      "js": [
        {
          "file": "assets/js/dda638a8.b2f23abe.js",
          "hash": "30565d9227d63546",
          "publicPath": "/cn/assets/js/dda638a8.b2f23abe.js"
        }
      ]
    },
    "3060": {
      "js": [
        {
          "file": "assets/js/b26cdafd.1448b942.js",
          "hash": "162b09498295780e",
          "publicPath": "/cn/assets/js/b26cdafd.1448b942.js"
        }
      ]
    },
    "3085": {
      "js": [
        {
          "file": "assets/js/1f391b9e.09dc2a1d.js",
          "hash": "e924d0aad8e9b487",
          "publicPath": "/cn/assets/js/1f391b9e.09dc2a1d.js"
        }
      ]
    },
    "3089": {
      "js": [
        {
          "file": "assets/js/a6aa9e1f.46f0fc52.js",
          "hash": "a3fc99981f5ad593",
          "publicPath": "/cn/assets/js/a6aa9e1f.46f0fc52.js"
        }
      ]
    },
    "3266": {
      "js": [
        {
          "file": "assets/js/c3804f3b.ab3194d7.js",
          "hash": "0d0c5308c3684913",
          "publicPath": "/cn/assets/js/c3804f3b.ab3194d7.js"
        }
      ]
    },
    "3514": {
      "js": [
        {
          "file": "assets/js/73664a40.bfdbe534.js",
          "hash": "bb2f7eede96a4300",
          "publicPath": "/cn/assets/js/73664a40.bfdbe534.js"
        }
      ]
    },
    "3608": {
      "js": [
        {
          "file": "assets/js/9e4087bc.289204bb.js",
          "hash": "93a6976aa06fb758",
          "publicPath": "/cn/assets/js/9e4087bc.289204bb.js"
        }
      ]
    },
    "3769": {
      "js": [
        {
          "file": "assets/js/e182be54.6211c794.js",
          "hash": "156ab1e296871b14",
          "publicPath": "/cn/assets/js/e182be54.6211c794.js"
        }
      ]
    },
    "3871": {
      "js": [
        {
          "file": "assets/js/4dfcf414.d916bc36.js",
          "hash": "40e9bfcf362ec3fb",
          "publicPath": "/cn/assets/js/4dfcf414.d916bc36.js"
        }
      ]
    },
    "4013": {
      "js": [
        {
          "file": "assets/js/01a85c17.de7e59ae.js",
          "hash": "d0b824d48a60139f",
          "publicPath": "/cn/assets/js/01a85c17.de7e59ae.js"
        }
      ]
    },
    "4138": {
      "js": [
        {
          "file": "assets/js/15548885.83abe3ec.js",
          "hash": "ed53b3d777571d45",
          "publicPath": "/cn/assets/js/15548885.83abe3ec.js"
        }
      ]
    },
    "4195": {
      "js": [
        {
          "file": "assets/js/c4f5d8e4.29022d68.js",
          "hash": "c4dc8b466d9b9c02",
          "publicPath": "/cn/assets/js/c4f5d8e4.29022d68.js"
        }
      ]
    },
    "4441": {
      "js": [
        {
          "file": "assets/js/efa918bb.fa785f34.js",
          "hash": "33a75e2c0776c011",
          "publicPath": "/cn/assets/js/efa918bb.fa785f34.js"
        }
      ]
    },
    "4466": {
      "js": [
        {
          "file": "assets/js/78027c79.7b24eb8d.js",
          "hash": "a66cae6eeba7868e",
          "publicPath": "/cn/assets/js/78027c79.7b24eb8d.js"
        }
      ]
    },
    "4521": {
      "js": [
        {
          "file": "assets/js/84d31fca.840f225e.js",
          "hash": "2651de7112b1246e",
          "publicPath": "/cn/assets/js/84d31fca.840f225e.js"
        }
      ]
    },
    "4608": {
      "js": [
        {
          "file": "assets/js/4608.85a54471.js",
          "hash": "142b553f5c2d62f5",
          "publicPath": "/cn/assets/js/4608.85a54471.js"
        },
        {
          "file": "assets/js/1be78505.dac99cfc.js",
          "hash": "000327348c8f0491",
          "publicPath": "/cn/assets/js/1be78505.dac99cfc.js"
        }
      ]
    },
    "4717": {
      "js": [
        {
          "file": "assets/js/20be1dc7.403bf030.js",
          "hash": "9c13a747fd002cda",
          "publicPath": "/cn/assets/js/20be1dc7.403bf030.js"
        }
      ]
    },
    "5440": {
      "js": [
        {
          "file": "assets/js/77869f04.18edb82f.js",
          "hash": "8d1fee546205aa39",
          "publicPath": "/cn/assets/js/77869f04.18edb82f.js"
        }
      ]
    },
    "6103": {
      "js": [
        {
          "file": "assets/js/ccc49370.bda19c62.js",
          "hash": "33682031503b87bf",
          "publicPath": "/cn/assets/js/ccc49370.bda19c62.js"
        }
      ]
    },
    "6499": {
      "js": [
        {
          "file": "assets/js/f5363f6c.b1e8c6d7.js",
          "hash": "bb987bbb80c1197e",
          "publicPath": "/cn/assets/js/f5363f6c.b1e8c6d7.js"
        }
      ]
    },
    "6839": {
      "js": [
        {
          "file": "assets/js/c91a8ac4.2e6ba5ce.js",
          "hash": "9db8066faed4d4b2",
          "publicPath": "/cn/assets/js/c91a8ac4.2e6ba5ce.js"
        }
      ]
    },
    "7070": {
      "js": [
        {
          "file": "assets/js/cff4a090.f576650f.js",
          "hash": "bd199c53e68988af",
          "publicPath": "/cn/assets/js/cff4a090.f576650f.js"
        }
      ]
    },
    "7076": {
      "js": [
        {
          "file": "assets/js/00b11949.188b2802.js",
          "hash": "f1fa2502b6e66b09",
          "publicPath": "/cn/assets/js/00b11949.188b2802.js"
        }
      ]
    },
    "7414": {
      "js": [
        {
          "file": "assets/js/393be207.bb4e8d89.js",
          "hash": "59d2fcdfac748bd7",
          "publicPath": "/cn/assets/js/393be207.bb4e8d89.js"
        }
      ]
    },
    "7459": {
      "js": [
        {
          "file": "assets/js/7459.04c3aae0.js",
          "hash": "a5b023ecfe64e53e",
          "publicPath": "/cn/assets/js/7459.04c3aae0.js"
        }
      ]
    },
    "7904": {
      "js": [
        {
          "file": "assets/js/d41956b8.28634090.js",
          "hash": "ae9b082af508ea4b",
          "publicPath": "/cn/assets/js/d41956b8.28634090.js"
        }
      ]
    },
    "7918": {
      "js": [
        {
          "file": "assets/js/17896441.e4f7d651.js",
          "hash": "6c207ae4ac1d169b",
          "publicPath": "/cn/assets/js/17896441.e4f7d651.js"
        }
      ]
    },
    "8329": {
      "js": [
        {
          "file": "assets/js/c37ce9b2.1ded640f.js",
          "hash": "543bb7412542919a",
          "publicPath": "/cn/assets/js/c37ce9b2.1ded640f.js"
        }
      ]
    },
    "8356": {
      "js": [
        {
          "file": "assets/js/074c9588.99495150.js",
          "hash": "ad40b5705d89d736",
          "publicPath": "/cn/assets/js/074c9588.99495150.js"
        }
      ]
    },
    "8392": {
      "js": [
        {
          "file": "assets/js/96548635.fe7894f7.js",
          "hash": "da08ee2e663691c4",
          "publicPath": "/cn/assets/js/96548635.fe7894f7.js"
        }
      ]
    },
    "8444": {
      "js": [
        {
          "file": "assets/js/b4fe1602.c7afe237.js",
          "hash": "77de205df2e42290",
          "publicPath": "/cn/assets/js/b4fe1602.c7afe237.js"
        }
      ]
    },
    "8592": {
      "js": [
        {
          "file": "assets/js/8712ed38.3a563290.js",
          "hash": "6717904dcf8e7a95",
          "publicPath": "/cn/assets/js/8712ed38.3a563290.js"
        }
      ]
    },
    "8610": {
      "js": [
        {
          "file": "assets/js/6875c492.59a315b4.js",
          "hash": "47c96eb3c3b900bb",
          "publicPath": "/cn/assets/js/6875c492.59a315b4.js"
        }
      ]
    },
    "8636": {
      "js": [
        {
          "file": "assets/js/f4f34a3a.b96b33ae.js",
          "hash": "2351d503720f56fe",
          "publicPath": "/cn/assets/js/f4f34a3a.b96b33ae.js"
        }
      ]
    },
    "9000": {
      "js": [
        {
          "file": "assets/js/4230b848.e6fcbfb2.js",
          "hash": "1b4858bbc5a6b6f5",
          "publicPath": "/cn/assets/js/4230b848.e6fcbfb2.js"
        }
      ]
    },
    "9003": {
      "js": [
        {
          "file": "assets/js/925b3f96.4204396a.js",
          "hash": "3aa43b5b2256f045",
          "publicPath": "/cn/assets/js/925b3f96.4204396a.js"
        }
      ]
    },
    "9174": {
      "js": [
        {
          "file": "assets/js/e379776a.2be06f8a.js",
          "hash": "bc7efc2f18926fb3",
          "publicPath": "/cn/assets/js/e379776a.2be06f8a.js"
        }
      ]
    },
    "9642": {
      "js": [
        {
          "file": "assets/js/7661071f.f9f0f6c7.js",
          "hash": "bb971cbe8f689881",
          "publicPath": "/cn/assets/js/7661071f.f9f0f6c7.js"
        }
      ]
    },
    "9643": {
      "js": [
        {
          "file": "assets/js/20623d08.41e729a7.js",
          "hash": "b0ef53c689e102a8",
          "publicPath": "/cn/assets/js/20623d08.41e729a7.js"
        }
      ]
    }
  }
}